dash_extensions_pkg/BeforeAfter.py
dash_extensions_pkg/CycleBreaker.py
dash_extensions_pkg/DeferScript.py
dash_extensions_pkg/EventListener.py
dash_extensions_pkg/EventSource.py
dash_extensions_pkg/Keyboard.py
dash_extensions_pkg/Loading.py
dash_extensions_pkg/Lottie.py
dash_extensions_pkg/Mermaid.py
dash_extensions_pkg/Purify.py
dash_extensions_pkg/ReconnectingWebSocket.py
dash_extensions_pkg/SSE.py
dash_extensions_pkg/WebSocket.py
dash_extensions_pkg/__init__.py
dash_extensions_pkg/_imports_.py
dash_extensions_pkg/async-BeforeAfter.js
dash_extensions_pkg/async-Lottie.js
dash_extensions_pkg/async-Mermaid.js
dash_extensions_pkg/async-Purify.js
dash_extensions_pkg/async-SSE.js
dash_extensions_pkg/async-null.js
dash_extensions_pkg/dash_extensions_pkg.js
dash_extensions_pkg/enrich.py
dash_extensions_pkg/events.py
dash_extensions_pkg/javascript.py
dash_extensions_pkg/logging.py
dash_extensions_pkg/metadata.json
dash_extensions_pkg/package-info.json
dash_extensions_pkg/pages.py
dash_extensions_pkg/proptypes.js
dash_extensions_pkg/snippets.py
dash_extensions_pkg/streaming.py
dash_extensions_pkg/utils.py
dash_extensions_pkg/validate.py
dash_extensions_pkg-2.0.13.dist-info/licenses/LICENSE
dash_extensions_pkg-2.0.13.dist-info/METADATA
dash_extensions_pkg-2.0.13.dist-info/WHEEL
dash_extensions_pkg-2.0.13.dist-info/top_level.txt
dash_extensions_pkg-2.0.13.dist-info/RECORD
